webnlg-corpus/__init__.py
webnlg-corpus/config.py
webnlg-corpus/downloader.py
webnlg-corpus/webnlg.py
webnlg_corpus/__init__.py
webnlg_corpus/config.py
webnlg_corpus/downloader.py
webnlg_corpus/webnlg.py
webnlg_corpus-0.1.dev10.dist-info/LICENSE
webnlg_corpus-0.1.dev10.dist-info/METADATA
webnlg_corpus-0.1.dev10.dist-info/WHEEL
webnlg_corpus-0.1.dev10.dist-info/top_level.txt
webnlg_corpus-0.1.dev10.dist-info/RECORD
