Metadata-Version: 2.1
Name: webnlg-corpus
Version: 0.1.dev10
Summary: WebNLG Corpus
Home-page: https://github.com/abevieiramota/webnlg_corpus
Author: Abelardo Vieira Mota
Author-email: abevieiramota@gmail.com
License: CC BY-NC-SA 4.0
Platform: UNKNOWN
Classifier: Intended Audience :: Education
Classifier: Programming Language :: Python :: 3
Classifier: Topic :: Scientific/Engineering :: Artificial Intelligence
Requires-Dist: pandas
Requires-Dist: tinydb
